[
  {
    "id": "HTK-1008",
    "name": "Minho Park",
    "age": 8,
    "program": "Little Dragon",
    "belt": "Yellow Stripe",
    "nextBelt": "Yellow Belt",
    "plan": "2 lessons/week",
    "attended": 7,
    "required": 15,
    "poomsae": 2,
    "poomsaeRequired": 3,
    "skills": 4,
    "skillsRequired": 5,
    "payment": "Overdue",
    "balance": 40000,
    "score": 47
  },
  {
    "id": "HTK-1042",
    "name": "Niyonsaba Aline",
    "age": 10,
    "program": "Kid Lesson",
    "belt": "Green Belt",
    "nextBelt": "Blue Stripe",
    "plan": "3 lessons/week",
    "attended": 14,
    "required": 15,
    "poomsae": 3,
    "poomsaeRequired": 3,
    "skills": 5,
    "skillsRequired": 5,
    "payment": "Paid",
    "balance": 0,
    "score": 93
  },
  {
    "id": "HTK-1077",
    "name": "Umutoni Diane",
    "age": 12,
    "program": "Teens & Adults",
    "belt": "Blue Stripe",
    "nextBelt": "Blue Belt",
    "plan": "2 lessons/week",
    "attended": 12,
    "required": 15,
    "poomsae": 3,
    "poomsaeRequired": 4,
    "skills": 4,
    "skillsRequired": 5,
    "payment": "Pending",
    "balance": 30000,
    "score": 78
  },
  {
    "id": "HTK-1099",
    "name": "Kamanzi Eric",
    "age": 15,
    "program": "Sparring Blue+",
    "belt": "Red Stripe",
    "nextBelt": "Red Belt",
    "plan": "3 lessons/week",
    "attended": 15,
    "required": 15,
    "poomsae": 5,
    "poomsaeRequired": 5,
    "skills": 5,
    "skillsRequired": 5,
    "payment": "Paid",
    "balance": 0,
    "score": 98
  }
]